mcising/__init__.py
mcising/ising_data_generate.py
mcising/isinglattice.py
mcising/montecarlo.py
tests/__init__.py
tests/test_isinglattice.py
tests/test_montecarlo.py
mcising-0.13.dist-info/LICENCE
mcising-0.13.dist-info/METADATA
mcising-0.13.dist-info/WHEEL
mcising-0.13.dist-info/entry_points.txt
mcising-0.13.dist-info/top_level.txt
mcising-0.13.dist-info/RECORD
