Metadata-Version: 2.1
Name: mcising
Version: 0.13
Summary: A package for generating Ising model data using Metropolis algorithm on a square lattice for nearest neighbor and next nearest neighbor interactions.
Home-page: https://github.com/bcivitcioglu/mcising
Author: Burak Ç.
Author-email: bcivitcioglu@gmail.com
Classifier: Programming Language :: Python :: 3
Classifier: License :: OSI Approved :: MIT License
Classifier: Operating System :: OS Independent
License-File: LICENCE
Requires-Dist: numpy
Requires-Dist: matplotlib
Requires-Dist: imageio
